{"name":"Pricebook2","fields":[{"length":18,"name":"Id","type":"id","defaultValue":null,"label":"Price Book ID","updateable":false,"precision":0,"scale":0,"controllerName":null,"unique":false,"byteLength":18,"calculated":false,"nameField":false,"sortable":true,"filterable":true,"nillable":false,"caseSensitive":false,"inlineHelpText":null,"writeRequiresMasterRead":false,"externalId":false,"idLookup":true,"createable":false,"soapType":"tns:ID","autoNumber":false,"restrictedPicklist":false,"namePointing":false,"custom":false,"defaultedOnCreate":true,"deprecatedAndHidden":false,"htmlFormatted":false,"defaultValueFormula":null,"calculatedFormula":null,"picklistValues":[],"dependentPicklist":false,"referenceTo":[],"relationshipName":null,"relationshipOrder":null,"cascadeDelete":false,"restrictedDelete":false,"digits":0,"groupable":true,"permissionable":false,"displayLocationInDecimal":false},{"length":40,"name":"Name","type":"string","defaultValue":null,"label":"Price Book Name","updateable":true,"precision":0,"scale":0,"controllerName":null,"unique":false,"byteLength":120,"calculated":false,"nameField":true,"sortable":true,"filterable":true,"nillable":false,"caseSensitive":false,"inlineHelpText":null,"writeRequiresMasterRead":false,"externalId":false,"idLookup":true,"createable":true,"soapType":"xsd:string","autoNumber":false,"restrictedPicklist":false,"namePointing":false,"custom":false,"defaultedOnCreate":false,"deprecatedAndHidden":false,"htmlFormatted":false,"defaultValueFormula":null,"calculatedFormula":null,"picklistValues":[],"dependentPicklist":false,"referenceTo":[],"relationshipName":null,"relationshipOrder":null,"cascadeDelete":false,"restrictedDelete":false,"digits":0,"groupable":true,"permissionable":false,"displayLocationInDecimal":false},{"length":0,"name":"IsActive","type":"boolean","defaultValue":null,"label":"Active","updateable":true,"precision":0,"scale":0,"controllerName":null,"unique":false,"byteLength":0,"calculated":false,"nameField":false,"sortable":true,"filterable":true,"nillable":false,"caseSensitive":false,"inlineHelpText":null,"writeRequiresMasterRead":false,"externalId":false,"idLookup":false,"createable":true,"soapType":"xsd:boolean","autoNumber":false,"restrictedPicklist":false,"namePointing":false,"custom":false,"defaultedOnCreate":true,"deprecatedAndHidden":false,"htmlFormatted":false,"defaultValueFormula":null,"calculatedFormula":null,"picklistValues":[],"dependentPicklist":false,"referenceTo":[],"relationshipName":null,"relationshipOrder":null,"cascadeDelete":false,"restrictedDelete":false,"digits":0,"groupable":true,"permissionable":false,"displayLocationInDecimal":false},{"length":0,"name":"LastModifiedDate","type":"datetime","defaultValue":null,"label":"Last Modified Date","updateable":false,"precision":0,"scale":0,"controllerName":null,"unique":false,"byteLength":0,"calculated":false,"nameField":false,"sortable":true,"filterable":true,"nillable":false,"caseSensitive":false,"inlineHelpText":null,"writeRequiresMasterRead":false,"externalId":false,"idLookup":false,"createable":false,"soapType":"xsd:dateTime","autoNumber":false,"restrictedPicklist":false,"namePointing":false,"custom":false,"defaultedOnCreate":true,"deprecatedAndHidden":false,"htmlFormatted":false,"defaultValueFormula":null,"calculatedFormula":null,"picklistValues":[],"dependentPicklist":false,"referenceTo":[],"relationshipName":null,"relationshipOrder":null,"cascadeDelete":false,"restrictedDelete":false,"digits":0,"groupable":false,"permissionable":false,"displayLocationInDecimal":false},{"length":0,"name":"SystemModstamp","type":"datetime","defaultValue":null,"label":"System Modstamp","updateable":false,"precision":0,"scale":0,"controllerName":null,"unique":false,"byteLength":0,"calculated":false,"nameField":false,"sortable":true,"filterable":true,"nillable":false,"caseSensitive":false,"inlineHelpText":null,"writeRequiresMasterRead":false,"externalId":false,"idLookup":false,"createable":false,"soapType":"xsd:dateTime","autoNumber":false,"restrictedPicklist":false,"namePointing":false,"custom":false,"defaultedOnCreate":true,"deprecatedAndHidden":false,"htmlFormatted":false,"defaultValueFormula":null,"calculatedFormula":null,"picklistValues":[],"dependentPicklist":false,"referenceTo":[],"relationshipName":null,"relationshipOrder":null,"cascadeDelete":false,"restrictedDelete":false,"digits":0,"groupable":false,"permissionable":false,"displayLocationInDecimal":false},{"length":0,"name":"IsStandard","type":"boolean","defaultValue":null,"label":"Is Standard Price Book","updateable":false,"precision":0,"scale":0,"controllerName":null,"unique":false,"byteLength":0,"calculated":false,"nameField":false,"sortable":true,"filterable":true,"nillable":false,"caseSensitive":false,"inlineHelpText":null,"writeRequiresMasterRead":false,"externalId":false,"idLookup":false,"createable":false,"soapType":"xsd:boolean","autoNumber":false,"restrictedPicklist":false,"namePointing":false,"custom":false,"defaultedOnCreate":true,"deprecatedAndHidden":false,"htmlFormatted":false,"defaultValueFormula":null,"calculatedFormula":null,"picklistValues":[],"dependentPicklist":false,"referenceTo":[],"relationshipName":null,"relationshipOrder":null,"cascadeDelete":false,"restrictedDelete":false,"digits":0,"groupable":true,"permissionable":false,"displayLocationInDecimal":false},{"length":255,"name":"Description","type":"string","defaultValue":null,"label":"Description","updateable":true,"precision":0,"scale":0,"controllerName":null,"unique":false,"byteLength":765,"calculated":false,"nameField":false,"sortable":true,"filterable":true,"nillable":true,"caseSensitive":false,"inlineHelpText":null,"writeRequiresMasterRead":false,"externalId":false,"idLookup":false,"createable":true,"soapType":"xsd:string","autoNumber":false,"restrictedPicklist":false,"namePointing":false,"custom":false,"defaultedOnCreate":false,"deprecatedAndHidden":false,"htmlFormatted":false,"defaultValueFormula":null,"calculatedFormula":null,"picklistValues":[],"dependentPicklist":false,"referenceTo":[],"relationshipName":null,"relationshipOrder":null,"cascadeDelete":false,"restrictedDelete":false,"digits":0,"groupable":true,"permissionable":false,"displayLocationInDecimal":false},{"length":18,"name":"LastModifiedById","type":"reference","defaultValue":null,"label":"Last Modified By ID","updateable":false,"precision":0,"scale":0,"controllerName":null,"unique":false,"byteLength":18,"calculated":false,"nameField":false,"sortable":true,"filterable":true,"nillable":false,"caseSensitive":false,"inlineHelpText":null,"writeRequiresMasterRead":false,"externalId":false,"idLookup":false,"createable":false,"soapType":"tns:ID","autoNumber":false,"restrictedPicklist":false,"namePointing":false,"custom":false,"defaultedOnCreate":true,"deprecatedAndHidden":false,"htmlFormatted":false,"defaultValueFormula":null,"calculatedFormula":null,"picklistValues":[],"dependentPicklist":false,"referenceTo":["User"],"relationshipName":"LastModifiedBy","relationshipOrder":null,"cascadeDelete":false,"restrictedDelete":false,"digits":0,"groupable":true,"permissionable":false,"displayLocationInDecimal":false},{"length":0,"name":"CreatedDate","type":"datetime","defaultValue":null,"label":"Created Date","updateable":false,"precision":0,"scale":0,"controllerName":null,"unique":false,"byteLength":0,"calculated":false,"nameField":false,"sortable":true,"filterable":true,"nillable":false,"caseSensitive":false,"inlineHelpText":null,"writeRequiresMasterRead":false,"externalId":false,"idLookup":false,"createable":false,"soapType":"xsd:dateTime","autoNumber":false,"restrictedPicklist":false,"namePointing":false,"custom":false,"defaultedOnCreate":true,"deprecatedAndHidden":false,"htmlFormatted":false,"defaultValueFormula":null,"calculatedFormula":null,"picklistValues":[],"dependentPicklist":false,"referenceTo":[],"relationshipName":null,"relationshipOrder":null,"cascadeDelete":false,"restrictedDelete":false,"digits":0,"groupable":false,"permissionable":false,"displayLocationInDecimal":false},{"length":18,"name":"CreatedById","type":"reference","defaultValue":null,"label":"Created By ID","updateable":false,"precision":0,"scale":0,"controllerName":null,"unique":false,"byteLength":18,"calculated":false,"nameField":false,"sortable":true,"filterable":true,"nillable":false,"caseSensitive":false,"inlineHelpText":null,"writeRequiresMasterRead":false,"externalId":false,"idLookup":false,"createable":false,"soapType":"tns:ID","autoNumber":false,"restrictedPicklist":false,"namePointing":false,"custom":false,"defaultedOnCreate":true,"deprecatedAndHidden":false,"htmlFormatted":false,"defaultValueFormula":null,"calculatedFormula":null,"picklistValues":[],"dependentPicklist":false,"referenceTo":["User"],"relationshipName":"CreatedBy","relationshipOrder":null,"cascadeDelete":false,"restrictedDelete":false,"digits":0,"groupable":true,"permissionable":false,"displayLocationInDecimal":false},{"length":0,"name":"IsDeleted","type":"boolean","defaultValue":null,"label":"Deleted","updateable":false,"precision":0,"scale":0,"controllerName":null,"unique":false,"byteLength":0,"calculated":false,"nameField":false,"sortable":true,"filterable":true,"nillable":false,"caseSensitive":false,"inlineHelpText":null,"writeRequiresMasterRead":false,"externalId":false,"idLookup":false,"createable":false,"soapType":"xsd:boolean","autoNumber":false,"restrictedPicklist":false,"namePointing":false,"custom":false,"defaultedOnCreate":true,"deprecatedAndHidden":false,"htmlFormatted":false,"defaultValueFormula":null,"calculatedFormula":null,"picklistValues":[],"dependentPicklist":false,"referenceTo":[],"relationshipName":null,"relationshipOrder":null,"cascadeDelete":false,"restrictedDelete":false,"digits":0,"groupable":true,"permissionable":false,"displayLocationInDecimal":false}],"label":"Price Book","updateable":true,"keyPrefix":"01s","custom":false,"labelPlural":"Price Books","layoutable":false,"activateable":false,"urls":{"uiEditTemplate":"https://na14.salesforce.com/{ID}/e","sobject":"/services/data/v26.0/sobjects/Pricebook2","uiDetailTemplate":"https://na14.salesforce.com/{ID}","describe":"/services/data/v26.0/sobjects/Pricebook2/describe","rowTemplate":"/services/data/v26.0/sobjects/Pricebook2/{ID}","uiNewRecord":"https://na14.salesforce.com/01s/e"},"searchable":false,"createable":true,"deprecatedAndHidden":false,"childRelationships":[{"field":"Pricebook2Id","deprecatedAndHidden":false,"relationshipName":"Opportunities","cascadeDelete":false,"restrictedDelete":true,"childSObject":"Opportunity"},{"field":"Pricebook2Id","deprecatedAndHidden":false,"relationshipName":"PricebookEntries","cascadeDelete":true,"restrictedDelete":false,"childSObject":"PricebookEntry"}],"customSetting":false,"deletable":true,"feedEnabled":false,"listviewable":null,"lookupLayoutable":null,"mergeable":false,"queryable":true,"recordTypeInfos":[],"replicateable":true,"retrieveable":true,"searchLayoutable":null,"undeletable":true,"triggerable":false}